{
  "dependencies": {
    "mssql1": {
      "serviceConnectorResourceId": "/subscriptions/[parameters('subscriptionId')]/resourcegroups/[parameters('serviceConnectorResourceGroupName')]/providers/Microsoft.Web/sites/backend20241115142223/providers/Microsoft.ServiceLinker/linkers/ConnectionStringsDefaultConnection_6A673F7D83",
      "secretStore": "AzureAppSettings",
      "resourceId": "/subscriptions/[parameters('subscriptionId')]/resourceGroups/[parameters('resourceGroupName')]/providers/Microsoft.Sql/servers/databasestoremanagementserver/databases/storeManagementdb",
      "type": "mssql.azure",
      "connectionId": "ConnectionStrings:DefaultConnection",
      "dynamicId": null
    },
    "apis1": {
      "ignored": "true",
      "type": "apis.azure"
    }
  }
}